contentcoder/ContentCoder.py
contentcoder/ContentCodingDictionary.py
contentcoder/__init__.py
contentcoder/create_export_dir.py
contentcoder/happiestfuntokenizing.py
contentcoder-1.0.5.dist-info/licenses/LICENSE
contentcoder-1.0.5.dist-info/METADATA
contentcoder-1.0.5.dist-info/WHEEL
contentcoder-1.0.5.dist-info/top_level.txt
contentcoder-1.0.5.dist-info/RECORD
