Metadata-Version: 2.4
Name: contentcoder
Version: 1.0.5
Summary: A generalized implementation of a dictionary-based content coder.
Author-email: "Ryan L. Boyd" <ryan@ryanboyd.io>
License-Expression: MIT
Project-URL: Homepage, https://github.com/ryanboyd/ContentCoder-Py
Project-URL: Issues, https://github.com/ryanboyd/ContentCoder-Py/issues
Classifier: Programming Language :: Python :: 3
Classifier: Programming Language :: Python :: 3 :: Only
Classifier: Programming Language :: Python :: 3.10
Classifier: Operating System :: OS Independent
Requires-Python: >=3.10
License-File: LICENSE
Dynamic: license-file
